protoc_gen_openapiv2/options/__init__.py
protoc_gen_openapiv2/options/annotations_pb2.py
protoc_gen_openapiv2/options/annotations_pb2.pyi
protoc_gen_openapiv2/options/openapiv2_pb2.py
protoc_gen_openapiv2/options/openapiv2_pb2.pyi
truera/__init__.py
truera/__main__.py
truera/constants.py
truera/artifactrepo/arlib/__init__.py
truera/artifactrepo/arlib/artifactrepolib.py
truera/artifactrepo/utils/__init__.py
truera/artifactrepo/utils/constants.py
truera/artifactrepo/utils/filter_utils.py
truera/artifactrepo/utils/proto_utils.py
truera/artifactrepo/utils/schema.py
truera/client/__init__.py
truera/client/base_truera_workspace.py
truera/client/cache.py
truera/client/client_environment.py
truera/client/client_pb_utils.py
truera/client/client_utils.py
truera/client/column_info.py
truera/client/constants.py
truera/client/data_source_utils.py
truera/client/errors.py
truera/client/feature_client.py
truera/client/ingestion_client.py
truera/client/model_preprocessing.py
truera/client/remote_truera_workspace.py
truera/client/truera_authentication.py
truera/client/truera_workspace.py
truera/client/truera_workspace_utils.py
truera/client/cli/BUILDINFO.txt
truera/client/cli/UncaughtExceptionHandler.py
truera/client/cli/__init__.py
truera/client/cli/activate.py
truera/client/cli/add.py
truera/client/cli/all.py
truera/client/cli/cli_logger.py
truera/client/cli/cli_utils.py
truera/client/cli/cli_version.txt
truera/client/cli/config.py
truera/client/cli/credential.py
truera/client/cli/data_source.py
truera/client/cli/delete.py
truera/client/cli/get.py
truera/client/cli/package.py
truera/client/cli/restore.py
truera/client/cli/run_model_on_data.py
truera/client/cli/sample.py
truera/client/cli/save.py
truera/client/cli/scheduled_ingestion.py
truera/client/cli/status.py
truera/client/cli/tru.py
truera/client/cli/verify.py
truera/client/cli/verify_nn_ingestion/__init__.py
truera/client/cli/verify_nn_ingestion/nlp.py
truera/client/cli/verify_nn_ingestion/timeseries.py
truera-12.6.1.dist-info/LICENSE.md
truera-12.6.1.dist-info/METADATA
truera-12.6.1.dist-info/WHEEL
truera-12.6.1.dist-info/entry_points.txt
truera-12.6.1.dist-info/top_level.txt
truera-12.6.1.dist-info/RECORD
