Metadata-Version: 2.1
Name: truera
Version: 12.6.1
Summary: Truera Python SDK.
Author: TruEra
Author-email: all@truera.com
License: Apache 2.0
Classifier: Programming Language :: Python :: 3
Classifier: Operating System :: OS Independent
Classifier: Development Status :: 3 - Alpha
Classifier: License :: OSI Approved :: Apache Software License
Requires-Python: >=3.8.6
License-File: LICENSE.md
Requires-Dist: cachetools >=5.2.0
Requires-Dist: click >=8.0
Requires-Dist: cloudpickle >=3.0.0
Requires-Dist: crontab >=1.0.1
Requires-Dist: cryptography >=42.0.0
Requires-Dist: dynaconf ==3.1.12
Requires-Dist: filelock >=3.0.12
Requires-Dist: googleapis-common-protos >=1.62.0
Requires-Dist: grpcio >=1.60.0
Requires-Dist: grpcio-status >=1.60.0
Requires-Dist: importlib-metadata >=4.8.1
Requires-Dist: nbformat >=5.1.2
Requires-Dist: pandas >=1.3.5
Requires-Dist: plotly >=5.11.0
Requires-Dist: prometheus-client >=0.14.0
Requires-Dist: protobuf >=4.25.2
Requires-Dist: pyarrow >=10.0.0
Requires-Dist: pydantic >=2.5.3
Requires-Dist: pyjwt >=2.4.0
Requires-Dist: python-dateutil >=2.8.1
Requires-Dist: pyyaml >=6.0.1
Requires-Dist: requests >=2.31.0
Requires-Dist: scikit-learn >=0.21.2
Requires-Dist: sqlparse ==0.4.4
Requires-Dist: tabulate >=0.8.9
Requires-Dist: tqdm >4.25.0
Requires-Dist: urllib3 >=1.25.8
Requires-Dist: humanize >=4.3.0
Requires-Dist: numpy <1.24.0
Requires-Dist: shap >=0.41.0
Requires-Dist: sympy >=1.10.1
Provides-Extra: llm
Requires-Dist: trulens-eval >=0.22.2 ; extra == 'llm'
Provides-Extra: nlp
Requires-Dist: attrs >=21.4.0 ; extra == 'nlp'
Requires-Dist: gensim >=4.2.0 ; extra == 'nlp'
Requires-Dist: ipywidgets ==7.7.2 ; extra == 'nlp'
Requires-Dist: Jinja2 >=3.0.3 ; extra == 'nlp'
Requires-Dist: matplotlib >=3.5.2 ; extra == 'nlp'
Requires-Dist: networkx >=2.5.1 ; extra == 'nlp'
Requires-Dist: nltk >=3.7 ; extra == 'nlp'
Requires-Dist: sumtypes >=0.1a6 ; extra == 'nlp'
Requires-Dist: threadpoolctl >=3.1.0 ; extra == 'nlp'
Requires-Dist: torch >=1.11.0 ; extra == 'nlp'
Requires-Dist: transformers >=4.19.2 ; extra == 'nlp'
Requires-Dist: trulens >=0.13.0 ; extra == 'nlp'
Requires-Dist: nltk >=3.8.1 ; extra == 'nlp'
Requires-Dist: pandarallel >=1.6.4 ; extra == 'nlp'
Requires-Dist: trulens-eval >=0.22.2 ; extra == 'nlp'
Provides-Extra: rnn
Requires-Dist: attrs >=21.4.0 ; extra == 'rnn'
Requires-Dist: boto3 >=1.17 ; extra == 'rnn'
Requires-Dist: dash >=2.2.0 ; extra == 'rnn'
Requires-Dist: dash-bootstrap-components >=0.12.2 ; extra == 'rnn'
Requires-Dist: diskcache >=5.4.0 ; extra == 'rnn'
Requires-Dist: ipywidgets ==7.7.2 ; extra == 'rnn'
Requires-Dist: Jinja2 >=3.0.3 ; extra == 'rnn'
Requires-Dist: jupyter-dash >=0.4.1 ; extra == 'rnn'
Requires-Dist: jupyterlab >=3 ; extra == 'rnn'
Requires-Dist: networkx >=2.5.1 ; extra == 'rnn'
Requires-Dist: progressbar >=2.5 ; extra == 'rnn'
Requires-Dist: sumtypes >=0.1a6 ; extra == 'rnn'
Requires-Dist: threadpoolctl >=3.1.0 ; extra == 'rnn'
Requires-Dist: trulens >=0.13.0 ; extra == 'rnn'
Provides-Extra: truera_qii
Requires-Dist: truera-qii >=0.39.20 ; extra == 'truera_qii'
Provides-Extra: viz
Requires-Dist: plotly >=5.11.0 ; extra == 'viz'
